mcp_vertica/__about__.py
mcp_vertica/__init__.py
mcp_vertica/connection.py
mcp_vertica/mcp.py
mcp_vertica-0.1.14.dist-info/METADATA
mcp_vertica-0.1.14.dist-info/WHEEL
mcp_vertica-0.1.14.dist-info/entry_points.txt
mcp_vertica-0.1.14.dist-info/licenses/LICENSE
mcp_vertica-0.1.14.dist-info/RECORD
