Metadata-Version: 2.4
Name: mcp-vertica
Version: 0.1.14
Summary: A Model Context Protocol (MCP) server for Vertica database with connection pooling, schema management, and security features
Project-URL: Homepage, https://github.com/nolleh/mcp-vertica
Project-URL: Repository, https://github.com/nolleh/mcp-vertica
Project-URL: Issues, https://github.com/nolleh/mcp-vertica/issues
Project-URL: Changelog, https://github.com/nolleh/mcp-vertica/releases
Project-URL: Documentation, https://github.com/nolleh/mcp-vertica#readme
Author-email: nolleh <nolleh7707@gmail.com>
Maintainer-email: nolleh <nolleh7707@gmail.com>
License: MIT
License-File: LICENSE
Keywords: ai,database,llm,mcp,model-context-protocol,vertica
Classifier: Development Status :: 4 - Beta
Classifier: Intended Audience :: Developers
Classifier: License :: OSI Approved :: MIT License
Classifier: Operating System :: OS Independent
Classifier: Programming Language :: Python :: 3
Classifier: Programming Language :: Python :: 3.12
Classifier: Programming Language :: Python :: 3.13
Classifier: Topic :: Database
Classifier: Topic :: Scientific/Engineering :: Artificial Intelligence
Classifier: Topic :: Software Development :: Libraries :: Python Modules
Requires-Python: >=3.12
Requires-Dist: click>=8.0.0
Requires-Dist: mcp[cli]
Requires-Dist: python-dotenv>=1.0.0
Requires-Dist: vertica-python>=1.0.0
